lutop/__init__.py
lutop/lutop.py
lutop-1.1.0.dist-info/LICENSE
lutop-1.1.0.dist-info/METADATA
lutop-1.1.0.dist-info/WHEEL
lutop-1.1.0.dist-info/entry_points.txt
lutop-1.1.0.dist-info/top_level.txt
lutop-1.1.0.dist-info/RECORD
