Metadata-Version: 2.1
Name: lutop
Version: 1.1.0
Summary: A utility to monitor system resources and top processes.
Home-page: https://github.com/barkhayot/lutop
Author: Barkhayot Juraev
Author-email: barkhayotoff@email.com
Keywords: system monitor processes
Classifier: Programming Language :: Python :: 3
Classifier: License :: OSI Approved :: MIT License
Classifier: Operating System :: OS Independent
Requires-Python: >=3.6
License-File: LICENSE
Requires-Dist: psutil
Requires-Dist: windows-curses ; platform_system == "Windows"
